{"receipt_id": "1237155-1002", "transaction_time": "2017-01-02 11:47:27.420", "products": [{"qty_sold": 0.87, "product_name": "Eataly Turkey Burger", "product_id": "14590-1000"}, {"qty_sold": 0.52, "product_name": "Tomato X Large Lucky", "product_id": "22386-1000"}, {"qty_sold": 1.01, "product_name": "Ravioli Di Ricotta", "product_id": "24551-1000"}, {"qty_sold": 2.0, "product_name": "Hamburger Bun", "product_id": "126-1000"}, {"qty_sold": 1.0, "product_name": "Lettuce Boston", "product_id": "21902-1000"}], "employee_name": "MUTIATU SANNI"}