{"receipt_id": "1240951-1002", "transaction_time": "2017-01-02 14:26:24.517", "products": [{"qty_sold": 2.0, "product_name": "Collard Greens", "product_id": "21617-1000"}, {"qty_sold": 1.95, "product_name": "Asparagus Purple", "product_id": "21228-1002"}, {"qty_sold": 0.46, "product_name": "Peppers Mixed Veggie Sweet", "product_id": "22139-1000"}, {"qty_sold": 1.0, "product_name": "Oranges Clementines Gift Box", "product_id": "22071-1000"}, {"qty_sold": 1.2, "product_name": "Lafrieda Hot Sausage", "product_id": "14615-1000"}, {"qty_sold": 1.0, "product_name": "Tin Mustard - Wholegrain 10Oz", "product_id": "6384-1000"}, {"qty_sold": 0.86, "product_name": "Apple Lady Fuji", "product_id": "21451-1000"}, {"qty_sold": 0.49, "product_name": "Pears Forelle", "product_id": "22109-1000"}], "employee_name": "Janel THOMAS"}