{"receipt_id": "1240267-1002", "transaction_time": "2017-01-02 14:02:07.313", "products": [{"qty_sold": 1.0, "product_name": "Berry Blackberries", "product_id": "21532-1000"}, {"qty_sold": 1.01, "product_name": "Chicken Thin Cut Breasts", "product_id": "14565-1000"}, {"qty_sold": 1.0, "product_name": "Truffle Sauce 180G", "product_id": "15667-1000"}, {"qty_sold": 1.0, "product_name": "Berry Raspberries Org. 4.4Oz", "product_id": "21548-1000"}, {"qty_sold": 1.0, "product_name": "Herbs Chives", "product_id": "21798-1000"}, {"qty_sold": 0.82, "product_name": "Mushroom Oyster", "product_id": "21977-1000"}, {"qty_sold": 2.0, "product_name": "White Moustache Quinc Yog 8 Oz", "product_id": "7325-1000"}, {"qty_sold": 0.41, "product_name": "Mushroom White Elf", "product_id": "21984-1000"}, {"qty_sold": 1.0, "product_name": "Rustic Classico", "product_id": "113-1000"}, {"qty_sold": 1.0, "product_name": "Berry Blueberries 4.4Oz", "product_id": "21534-1000"}, {"qty_sold": 1.0, "product_name": "Fc Salad Rocat Arugula 103Oz", "product_id": "21703-1000"}, {"qty_sold": 1.23, "product_name": "Potato Yukon -A- (Large)", "product_id": "22212-1000"}, {"qty_sold": 0.33, "product_name": "Frisse California", "product_id": "21754-1000"}, {"qty_sold": 1.0, "product_name": "Unsalted Cultured Butter 8 Oz", "product_id": "7253-1000"}, {"qty_sold": 0.53, "product_name": "Mushroom Cremini Organic", "product_id": "21961-1000"}, {"qty_sold": 0.5, "product_name": "Mushroom Maitake Organic", "product_id": "21973-1000"}, {"qty_sold": 1.62, "product_name": "Halibut Atlantic", "product_id": "7656-1000"}], "employee_name": "Karen Rios"}