{"receipt_id": "1240623-1002", "transaction_time": "2017-01-02 14:15:02.193", "products": [{"qty_sold": 1.01, "product_name": "Chicken Thin Cut Breasts", "product_id": "14565-1000"}, {"qty_sold": 0.69, "product_name": "Onions Sweet", "product_id": "22048-1000"}, {"qty_sold": 0.56, "product_name": "Sottocenere With Truffles", "product_id": "4461-1000"}, {"qty_sold": 0.58, "product_name": "Gorgonzola Dolce Creamy", "product_id": "4508-1000"}, {"qty_sold": 1.0, "product_name": "Peeled San Marzano Toms 14.1Oz", "product_id": "15327-1000"}, {"qty_sold": 1.0, "product_name": "Celery Organic", "product_id": "21603-1000"}, {"qty_sold": 1.0, "product_name": "Spinach Bunched", "product_id": "22282-1000"}, {"qty_sold": 1.0, "product_name": "2% 1/2 Gallon Milk", "product_id": "7101-1000"}, {"qty_sold": 1.18, "product_name": "Bolognese Ragu Mix", "product_id": "14523-1000"}, {"qty_sold": 0.32, "product_name": "Levoni Pancetta Cotto", "product_id": "16368-1000"}, {"qty_sold": 1.0, "product_name": "Rhododendrun Honey 4.76 Oz", "product_id": "17347-1000"}, {"qty_sold": 1.0, "product_name": "Lemon", "product_id": "21880-1000"}, {"qty_sold": 1.0, "product_name": "Caserecce Gluten Free 1 Lb", "product_id": "9136-1000"}, {"qty_sold": 1.0, "product_name": "Carrots Bunched Org.", "product_id": "21585-1000"}], "employee_name": "CRYSTAL SANDERS"}