{"receipt_id": "1241403-1002", "transaction_time": "2017-01-02 14:39:28.413", "products": [{"qty_sold": 0.25, "product_name": "Prosciutto 24 Months - Tanara", "product_id": "16230-1000"}, {"qty_sold": 1.0, "product_name": "Roasted Garlic Hummus 7 Oz", "product_id": "5954-1000"}, {"qty_sold": 1.0, "product_name": "Eataly Mixed Berries 10 Oz", "product_id": "21665-1000"}, {"qty_sold": 1.0, "product_name": "Redfife Crackers 6.5Oz", "product_id": "9097-1000"}, {"qty_sold": 1.0, "product_name": "Fc Mangos Chunks 10Oz", "product_id": "21694-1000"}, {"qty_sold": 1.0, "product_name": "Melighe Cookies 7.8 Oz", "product_id": "16542-1000"}, {"qty_sold": 0.55, "product_name": "Pecorino Al Tartufo (Lazio)", "product_id": "5345-1000"}], "employee_name": "Joanna Reese"}