{"receipt_id": "1242031-1002", "transaction_time": "2017-01-02 14:57:36.387", "products": [{"qty_sold": 1.0, "product_name": "Leeks Baby", "product_id": "21878-1000"}, {"qty_sold": 1.0, "product_name": "Celery", "product_id": "21600-1000"}, {"qty_sold": 1.0, "product_name": "Cauliflower", "product_id": "21592-1000"}, {"qty_sold": 1.0, "product_name": "Carrots Bunched Org.", "product_id": "21585-1000"}, {"qty_sold": 0.83, "product_name": "Romaine Heart Baby", "product_id": "22243-1000"}, {"qty_sold": 1.0, "product_name": "Berry Blackberries Organic", "product_id": "21533-1000"}, {"qty_sold": 1.3, "product_name": "Squash  Med Org Green", "product_id": "22286-1000"}], "employee_name": "Karen Rios"}