{"receipt_id": "1246151-1002", "transaction_time": "2017-01-02 17:06:32.803", "products": [{"qty_sold": 0.2, "product_name": "Grana Padano 18Mo", "product_id": "4419-1000"}, {"qty_sold": 0.56, "product_name": "Brussels Sprouts", "product_id": "24302-1000"}, {"qty_sold": 1.0, "product_name": "Bianca Spaghetti Pasta 17.6Oz", "product_id": "8804-1000"}, {"qty_sold": 0.4, "product_name": "Levoni Mortadella W/ Pistachio", "product_id": "16152-1000"}, {"qty_sold": 1.0, "product_name": "Semolina Baguette", "product_id": "121-1000"}, {"qty_sold": 0.21, "product_name": "Prosciutto 24 Months - Tanara", "product_id": "16230-1000"}, {"qty_sold": 0.53, "product_name": "Liuzzi Ricotta", "product_id": "4342-1000"}, {"qty_sold": 0.77, "product_name": "Pancetta Pepato", "product_id": "16160-1000"}], "employee_name": "Mariel Mital"}