{"receipt_id": "1246883-1002", "transaction_time": "2017-01-02 17:31:44.477", "products": [{"qty_sold": 0.53, "product_name": "Smoked Duck Breast", "product_id": "14695-1000"}, {"qty_sold": 1.51, "product_name": "Potato Yams Jumbo", "product_id": "22211-1000"}, {"qty_sold": 1.0, "product_name": "Carrots Bunched Org.", "product_id": "21585-1000"}, {"qty_sold": 1.87, "product_name": "Pears Red", "product_id": "22110-1000"}, {"qty_sold": 1.0, "product_name": "Ciabatta", "product_id": "148-1000"}, {"qty_sold": 0.84, "product_name": "Lettuce Escarole Italian", "product_id": "21906-1000"}, {"qty_sold": 0.13, "product_name": "Garlic Christopher Ranch", "product_id": "21760-1000"}, {"qty_sold": 0.47, "product_name": "Onions Red", "product_id": "22041-1000"}, {"qty_sold": 1.0, "product_name": "Herbs Basil", "product_id": "21791-1000"}, {"qty_sold": 1.0, "product_name": "Chicken Stock Small", "product_id": "15001-1000"}, {"qty_sold": 1.51, "product_name": "Apple Honeycrisp Org.", "product_id": "21445-1000"}], "employee_name": "Mariel Mital"}