{"receipt_id": "1249019-1002", "transaction_time": "2017-01-02 19:06:51.273", "products": [{"qty_sold": 1.0, "product_name": "Pomegranates Seeds", "product_id": "22190-1000"}, {"qty_sold": 2.39, "product_name": "Potato Idaho   80", "product_id": "22200-1000"}, {"qty_sold": 0.6, "product_name": "Eataly Turkey Sausage", "product_id": "14576-1000"}, {"qty_sold": 1.04, "product_name": "Asparagus White", "product_id": "21498-1000"}, {"qty_sold": 1.0, "product_name": "Berry Raspberries Org. 4.4Oz", "product_id": "21548-1000"}, {"qty_sold": 1.35, "product_name": "Cascun Farm Chicken Breast", "product_id": "14604-1000"}, {"qty_sold": 0.51, "product_name": "Grilled Artichokes Stems", "product_id": "37-1000"}, {"qty_sold": 1.01, "product_name": "Prosciutto 24 Months - Tanara", "product_id": "16230-1000"}, {"qty_sold": 1.0, "product_name": "Carrots Organic Baby Peeled 24X1", "product_id": "21589-1000"}, {"qty_sold": 1.0, "product_name": "Fc Salad Baby Arugula 5Oz", "product_id": "21699-1000"}, {"qty_sold": 0.52, "product_name": "Olives Pitted Country Mix", "product_id": "48-1000"}], "employee_name": "Tenyjah Nibbs"}