{"receipt_id": "1250311-1002", "transaction_time": "2017-01-02 20:25:07.210", "products": [{"qty_sold": 1.0, "product_name": "Unsalted Butter Tube 8Oz", "product_id": "7106-1000"}, {"qty_sold": 1.0, "product_name": "Fc Salad Baby Spinach 5Oz", "product_id": "21700-1000"}, {"qty_sold": 1.0, "product_name": "Tomato Grape Org.", "product_id": "22351-1000"}, {"qty_sold": 1.0, "product_name": "2% 1/2 Gallon Milk", "product_id": "7101-1000"}, {"qty_sold": 1.0, "product_name": "Semolina Baguette", "product_id": "121-1000"}], "employee_name": "Alberine Rivera"}