{"receipt_id": "1253403-1002", "transaction_time": "2017-01-03 10:07:44.177", "products": [{"qty_sold": 1.0, "product_name": "Bottle Deposit", "product_id": "21410-1000"}, {"qty_sold": 1.0, "product_name": "White Truffle Supplement Pan $3", "product_id": "24911-1000"}, {"qty_sold": 1.0, "product_name": "Aranciata Blood Oran Can 11 Oz", "product_id": "1469-1000"}, {"qty_sold": 1.0, "product_name": "Aosta Breakfast Panini", "product_id": "14766-1000"}, {"qty_sold": 0.27, "product_name": "Imported Bresaola", "product_id": "16103-1000"}], "employee_name": "PANINI AM"}