{"receipt_id": "1265787-1002", "transaction_time": "2017-01-03 19:42:44.197", "products": [{"qty_sold": 1.0, "product_name": "Torino 56% Dark Bar 3.5 Oz", "product_id": "17852-1000"}, {"qty_sold": 0.43, "product_name": "Mushroom Cremini", "product_id": "21960-1000"}, {"qty_sold": 1.0, "product_name": "Hot Pepper Sauce 1.2 Oz", "product_id": "15103-1000"}, {"qty_sold": 0.28, "product_name": "Prosciutto 24 Months - Tanara", "product_id": "16230-1000"}, {"qty_sold": 1.0, "product_name": "Classic Baguette", "product_id": "193-1000"}, {"qty_sold": 1.03, "product_name": "Pansotti Liguri", "product_id": "7897-1000"}], "employee_name": "DAVID WINDMULLER"}