{"receipt_id": "1266147-1002", "transaction_time": "2017-01-03 20:02:22.940", "products": [{"qty_sold": 1.0, "product_name": "Berry Blueberries 4.4Oz", "product_id": "21534-1000"}, {"qty_sold": 1.0, "product_name": "Eggs Large 1/2 Doz Hidden Camp", "product_id": "7334-1000"}, {"qty_sold": 1.0, "product_name": "Pomegranates Seeds", "product_id": "22190-1000"}, {"qty_sold": 0.56, "product_name": "Olives Cerignola Green", "product_id": "25-1000"}, {"qty_sold": 2.35, "product_name": "Bananas", "product_id": "21504-1000"}, {"qty_sold": 1.0, "product_name": "Brussel Baby 10X500", "product_id": "21565-1000"}, {"qty_sold": 2.0, "product_name": "Lemon", "product_id": "21880-1000"}, {"qty_sold": 1.0, "product_name": "Almond Butter 12Oz", "product_id": "21215-1002"}, {"qty_sold": 0.61, "product_name": "Potato Yams Jumbo", "product_id": "22211-1000"}, {"qty_sold": 2.6, "product_name": "Chicken", "product_id": "16080-1000"}], "employee_name": "Brittany King"}