{"receipt_id": "1270583-1002", "transaction_time": "2017-01-04 11:29:59.443", "products": [{"qty_sold": 5.0, "product_name": "Avocado Hass", "product_id": "21500-1000"}, {"qty_sold": 1.0, "product_name": "Fc Salad Primo Mesclun", "product_id": "21702-1000"}, {"qty_sold": 1.0, "product_name": "Lemon", "product_id": "21880-1000"}, {"qty_sold": 1.0, "product_name": "Tomato Grape Org.", "product_id": "22351-1000"}, {"qty_sold": 2.0, "product_name": "Limes", "product_id": "21922-1000"}], "employee_name": "YASH-SHAKAR KING"}