{"receipt_id": "1272591-1002", "transaction_time": "2017-01-04 12:59:27.283", "products": [{"qty_sold": 1.0, "product_name": "Ziti Corti Rigati 17.6Oz", "product_id": "8552-1000"}, {"qty_sold": 1.0, "product_name": "Classic Baguette", "product_id": "193-1000"}, {"qty_sold": 1.0, "product_name": "Rigorosa Linguine 17.6Oz", "product_id": "8565-1000"}, {"qty_sold": 1.0, "product_name": "Swiss Chard Rainbow Org.", "product_id": "22333-1000"}, {"qty_sold": 1.0, "product_name": "Red Wine Vinegar 16.9 Oz", "product_id": "5732-1000"}, {"qty_sold": 1.0, "product_name": "Pasta With Olives 8.8Oz", "product_id": "8791-1000"}, {"qty_sold": 1.0, "product_name": "Fusilli 17.6 Oz", "product_id": "24750-1000"}, {"qty_sold": 1.0, "product_name": "Mediterraneo", "product_id": "23614-1000"}, {"qty_sold": 1.0, "product_name": "Fruttato Evoo 16.9Oz", "product_id": "6204-1000"}], "employee_name": "Catherine Rebollar"}