{"receipt_id": "1277303-1002", "transaction_time": "2017-01-04 15:37:08.053", "products": [{"qty_sold": 0.76, "product_name": "Prime Rib Rotisserie", "product_id": "16096-1000"}, {"qty_sold": 0.99, "product_name": "Bananas", "product_id": "21504-1000"}, {"qty_sold": 1.0, "product_name": "Walnut Raisin Sourdough", "product_id": "270-1000"}, {"qty_sold": 1.34, "product_name": "Grapes Green Seedless", "product_id": "21776-1000"}, {"qty_sold": 0.4, "product_name": "Peas English", "product_id": "22112-1000"}, {"qty_sold": 0.15, "product_name": "Garlic Christopher Ranch", "product_id": "21760-1000"}, {"qty_sold": 0.12, "product_name": "Peppers Jalapenos", "product_id": "22137-1000"}, {"qty_sold": 0.67, "product_name": "Braised Brisket Meatball", "product_id": "23101-1000"}, {"qty_sold": 1.0, "product_name": "Bread Bag Medium Silver", "product_id": "25219-1000"}, {"qty_sold": 2.0, "product_name": "Limes", "product_id": "21922-1000"}, {"qty_sold": 1.0, "product_name": "Melon Honeydews", "product_id": "21946-1000"}], "employee_name": "Herbert Borrero"}