{"receipt_id": "1280223-1002", "transaction_time": "2017-01-04 17:29:33.873", "products": [{"qty_sold": 2.02, "product_name": "Chopped Meatball Mix", "product_id": "14506-1000"}, {"qty_sold": 0.9, "product_name": "Organic Salmon", "product_id": "25101-1000"}, {"qty_sold": 1.0, "product_name": "Kale Green Org", "product_id": "21861-1000"}, {"qty_sold": 0.99, "product_name": "Agnolotti Del Plin Brasato", "product_id": "7896-1000"}, {"qty_sold": 1.0, "product_name": "Garlic Peeled Fresh California 4", "product_id": "21765-1000"}, {"qty_sold": 1.0, "product_name": "Onion Diced Organic 1210Oz Ur", "product_id": "22020-1000"}, {"qty_sold": 0.92, "product_name": "Parmigiano Reggiano 36Mo", "product_id": "4428-1000"}, {"qty_sold": 0.79, "product_name": "Beets And Walnuts", "product_id": "24301-1000"}, {"qty_sold": 1.0, "product_name": "Dried Figs 7.05 Oz", "product_id": "15653-1000"}], "employee_name": "Tenyjah Nibbs"}