{"receipt_id": "1281119-1002", "transaction_time": "2017-01-04 18:01:33.173", "products": [{"qty_sold": 0.31, "product_name": "Radicchio Castillo Franco Italia", "product_id": "22225-1000"}, {"qty_sold": 0.48, "product_name": "Olives Castelvetrano", "product_id": "30-1000"}, {"qty_sold": 1.0, "product_name": "Fennel  Anise", "product_id": "21709-1000"}, {"qty_sold": 0.29, "product_name": "Prosciutto 18 Months - Tanara", "product_id": "16229-1000"}, {"qty_sold": 0.42, "product_name": "Endive Red", "product_id": "21682-1000"}, {"qty_sold": 0.56, "product_name": "Lettuce Little Gem", "product_id": "21910-1000"}, {"qty_sold": 0.78, "product_name": "Potato Fingerling Russian", "product_id": "22198-1000"}, {"qty_sold": 0.32, "product_name": "Tajarin", "product_id": "7978-1000"}, {"qty_sold": 1.0, "product_name": "Ragu Bolognese 7.05 Oz", "product_id": "16021-1000"}, {"qty_sold": 2.78, "product_name": "Chicken", "product_id": "16080-1000"}], "employee_name": "DAVID WINDMULLER"}