{"receipt_id": "1282083-1002", "transaction_time": "2017-01-04 18:34:27.787", "products": [{"qty_sold": 1.0, "product_name": "Baci Di Dama Cookies 1Oz", "product_id": "17924-1000"}, {"qty_sold": 1.0, "product_name": "Bacio - Display", "product_id": "17111-1000"}, {"qty_sold": 1.0, "product_name": "Loacker Classic Lemon 45 G", "product_id": "17591-1000"}, {"qty_sold": 1.0, "product_name": "Mozzarella Classica 5 Oz 1Pc", "product_id": "5202-1000"}, {"qty_sold": 1.0, "product_name": "Dolce Ground Coffee 8.8Oz", "product_id": "4158-1000"}, {"qty_sold": 1.0, "product_name": "Special Bar Grnd Coffee 8.8Oz", "product_id": "4159-1000"}], "employee_name": "Brittany King"}