{"receipt_id": "1286171-1002", "transaction_time": "2017-01-04 22:41:34.523", "products": [{"qty_sold": 1.0, "product_name": "Lidia Master Italian Cuisine", "product_id": "3664-1000"}, {"qty_sold": 0.81, "product_name": "Parmigiano Cravero 24Mo", "product_id": "4477-1000"}, {"qty_sold": 1.0, "product_name": "Mezze Maniche Rigate", "product_id": "8782-1000"}, {"qty_sold": 1.0, "product_name": "Black Olive Bruschetta 3.5 Oz", "product_id": "15099-1000"}, {"qty_sold": 1.0, "product_name": "Anch. Oil W/ Capers 3.17Oz Jar", "product_id": "15416-1000"}, {"qty_sold": 2.0, "product_name": "Kilimanjaro Single Origin 12Oz", "product_id": "4263-1000"}, {"qty_sold": 1.0, "product_name": "Cav Riserva Nando", "product_id": "5783-1000"}, {"qty_sold": 1.0, "product_name": "Casarecci 1.1 Lb", "product_id": "9264-1000"}, {"qty_sold": 2.0, "product_name": "Organic Tomato Puree 24.3 Oz", "product_id": "15136-1000"}, {"qty_sold": 2.0, "product_name": "Basil Pesto 6.3 Oz", "product_id": "15167-1000"}, {"qty_sold": 1.0, "product_name": "Apricot Preserves 7.4 Oz", "product_id": "15316-1000"}, {"qty_sold": 2.0, "product_name": "Bag With Zip Raspberry", "product_id": "13054-1000"}, {"qty_sold": 1.0, "product_name": "Balsamic Vin Capr Di Vale8.5Oz", "product_id": "5943-1000"}, {"qty_sold": 1.0, "product_name": "Splendido Evoo 16.9 Oz", "product_id": "6094-1000"}, {"qty_sold": 1.0, "product_name": "Grilled Artichokes 10.2 Oz", "product_id": "15096-1000"}, {"qty_sold": 1.0, "product_name": "Babbo Cookbook\\Batali Mario", "product_id": "1528-1000"}, {"qty_sold": 1.0, "product_name": "Prune Preserves 7.4 Oz", "product_id": "15320-1000"}, {"qty_sold": 1.0, "product_name": "Mediterranean Sauce 7 Oz", "product_id": "15942-1000"}, {"qty_sold": 1.0, "product_name": "Ursini Chiet Ev Olve Oil 8.5Oz", "product_id": "5667-1000"}, {"qty_sold": 1.0, "product_name": "Semolina (Grano Duro) 35 Oz", "product_id": "9283-1000"}, {"qty_sold": 2.77, "product_name": "Pick And Mix Venchi", "product_id": "18056-1000"}, {"qty_sold": 1.0, "product_name": "Green Vegetable Sauce 7.05 Oz", "product_id": "15253-1000"}, {"qty_sold": 2.0, "product_name": "Pandolcino Cookies 1.75Oz", "product_id": "17931-1000"}, {"qty_sold": 1.0, "product_name": "Tshirt, All I Want For Xmas, Xl", "product_id": "24684-1000"}], "employee_name": "Alberine Rivera"}