{"receipt_id": "1288355-1002", "transaction_time": "2017-01-05 10:42:21.797", "products": [{"qty_sold": 1.0, "product_name": "To Go", "product_id": "23552-1000"}, {"qty_sold": 1.0, "product_name": "Latte Macchiato Medium", "product_id": "23474-1000"}, {"qty_sold": 0.78, "product_name": "Apple Gala Org.", "product_id": "21426-1000"}, {"qty_sold": 1.0, "product_name": "Avocado Hass", "product_id": "21500-1000"}, {"qty_sold": 1.0, "product_name": "Decaf", "product_id": "23495-1000"}, {"qty_sold": 1.0, "product_name": "Berry Raspberries Org. 4.4Oz", "product_id": "21548-1000"}, {"qty_sold": 1.07, "product_name": "Bananas", "product_id": "21504-1000"}], "employee_name": "Gran Bar AM Eataly Flat Iron"}