{"receipt_id": "1293379-1002", "transaction_time": "2017-01-05 14:22:25.127", "products": [{"qty_sold": 1.0, "product_name": "No Sugar Cereal Cookies 8.5Oz", "product_id": "17500-1000"}, {"qty_sold": 1.0, "product_name": "Bocconcino Di Alta Langa", "product_id": "4993-1000"}, {"qty_sold": 1.0, "product_name": "Classic Baguette", "product_id": "193-1000"}, {"qty_sold": 0.24, "product_name": "Imported Bresaola", "product_id": "16103-1000"}, {"qty_sold": 1.0, "product_name": "Weybridge", "product_id": "4584-1000"}], "employee_name": "Albert Berroa"}