{"receipt_id": "1294195-1002", "transaction_time": "2017-01-05 14:52:39.603", "products": [{"qty_sold": 0.48, "product_name": "Peppers Shishito", "product_id": "22149-1000"}, {"qty_sold": 2.0, "product_name": "Bacio - Display", "product_id": "17111-1000"}, {"qty_sold": 0.59, "product_name": "Taleggio Brescialat", "product_id": "4515-1000"}, {"qty_sold": 0.41, "product_name": "Onions Red", "product_id": "22041-1000"}, {"qty_sold": 0.31, "product_name": "Speck Recla", "product_id": "16423-1000"}, {"qty_sold": 0.81, "product_name": "Radicchio Trevisano", "product_id": "22228-1000"}], "employee_name": "Albert Berroa"}