{"receipt_id": "1298895-1002", "transaction_time": "2017-01-05 17:53:42.403", "products": [{"qty_sold": 0.14, "product_name": "Garlic Christopher Ranch", "product_id": "21760-1000"}, {"qty_sold": 2.0, "product_name": "Grapefruit Loose Large", "product_id": "21772-1000"}, {"qty_sold": 1.0, "product_name": "Fc Salad Baby Arugula 5Oz", "product_id": "21699-1000"}, {"qty_sold": 1.0, "product_name": "Tomato Heirloom Kumato", "product_id": "22359-1000"}, {"qty_sold": 1.0, "product_name": "Mini Basting Brush", "product_id": "12320-1000"}], "employee_name": "CRYSTAL SANDERS"}