{"receipt_id": "1300199-1002", "transaction_time": "2017-01-05 18:47:33.977", "products": [{"qty_sold": 0.97, "product_name": "Levoni Mortadella Oro", "product_id": "16151-1000"}, {"qty_sold": 0.54, "product_name": "Olives Castelvetrano", "product_id": "30-1000"}, {"qty_sold": 0.49, "product_name": "Prosciutto 18 Months - Tanara", "product_id": "16229-1000"}, {"qty_sold": 1.0, "product_name": "Berry Raspberries Org. 4.4Oz", "product_id": "21548-1000"}, {"qty_sold": 2.13, "product_name": "Whole Quail", "product_id": "14624-1000"}, {"qty_sold": 0.34, "product_name": "Speck Recla", "product_id": "16423-1000"}, {"qty_sold": 2.0, "product_name": "Berry Blueberries 4.4Oz", "product_id": "21534-1000"}, {"qty_sold": 1.0, "product_name": "Berry Raspberries", "product_id": "21546-1000"}, {"qty_sold": 2.0, "product_name": "Berry Currants Red", "product_id": "21543-1000"}, {"qty_sold": 0.27, "product_name": "Onions Shallots", "product_id": "22044-1000"}, {"qty_sold": 2.96, "product_name": "Tomato Heirloom", "product_id": "22355-1000"}, {"qty_sold": 0.55, "product_name": "Olives Cerignola Green", "product_id": "25-1000"}, {"qty_sold": 1.05, "product_name": "Chicken Livers (Traypack)", "product_id": "14575-1000"}], "employee_name": "Alberine Rivera"}