{"receipt_id": "1302547-1002", "transaction_time": "2017-01-05 20:42:39.210", "products": [{"qty_sold": 1.02, "product_name": "Potatoes Roasted", "product_id": "16091-1000"}, {"qty_sold": 1.0, "product_name": "Lettuce Org.Red Leaf", "product_id": "21917-1000"}, {"qty_sold": 1.0, "product_name": "Onions Scallions Organic", "product_id": "22043-1000"}, {"qty_sold": 1.0, "product_name": "Lettuce Boston", "product_id": "21902-1000"}, {"qty_sold": 1.0, "product_name": "Carrots Bunched Org.", "product_id": "21585-1000"}, {"qty_sold": 2.66, "product_name": "Chicken", "product_id": "16080-1000"}, {"qty_sold": 1.0, "product_name": "Celery Organic", "product_id": "21603-1000"}, {"qty_sold": 1.0, "product_name": "Lettuce Satur Farm", "product_id": "21912-1000"}], "employee_name": "Janel THOMAS"}