{"receipt_id": "421534-1004", "transaction_time": "2017-01-02 19:33:39.550", "products": [{"qty_sold": 1.0, "product_name": "Loacker Classic Vanilla 175 G", "product_id": "17596-1000"}, {"qty_sold": 1.0, "product_name": "Lunette Cookies 1.75Oz", "product_id": "17915-1000"}, {"qty_sold": 2.0, "product_name": "Corn Cookies W Sugar 10.25Oz", "product_id": "17918-1000"}, {"qty_sold": 1.0, "product_name": "Raspberry-Ygt 150 G", "product_id": "17942-1000"}, {"qty_sold": 1.0, "product_name": "No Sugar Classic Cookies 8.5Oz", "product_id": "17499-1000"}], "employee_name": "Alex Cornwell"}