{"receipt_id": "423714-1004", "transaction_time": "2017-01-03 15:27:10.227", "products": [{"qty_sold": 2.0, "product_name": "9\" Classic Baguette", "product_id": "125-1000"}, {"qty_sold": 0.51, "product_name": "Mortadella Pistachio (Fontana)", "product_id": "16139-1000"}, {"qty_sold": 0.53, "product_name": "Prosciutto 24 Months - Tanara", "product_id": "16230-1000"}, {"qty_sold": 1.0, "product_name": "Ribolla Adriatico 2013", "product_id": "20140-1000"}, {"qty_sold": 1.0, "product_name": "Mozzarella Classica 8Oz", "product_id": "23047-1004"}, {"qty_sold": 0.45, "product_name": "Ricotta Calabro Fresh Cone", "product_id": "4475-1000"}], "employee_name": "Amber Brown"}