{"receipt_id": "425738-1004", "transaction_time": "2017-01-04 10:04:39.197", "products": [{"qty_sold": 1.0, "product_name": "Unsalted Cultured Butter 8 Oz", "product_id": "7253-1000"}, {"qty_sold": 2.0, "product_name": "Fresh Pizza Dough", "product_id": "24166-1000"}, {"qty_sold": 1.0, "product_name": "Kilgus 2% Milk Pint", "product_id": "7272-1000"}, {"qty_sold": 0.48, "product_name": "Pasta Salad", "product_id": "21183-1000"}, {"qty_sold": 1.0, "product_name": "White Truffle Butter 3 Oz", "product_id": "7018-1000"}], "employee_name": "Chicago Amazon Eataly Chicago"}