{"receipt_id": "428478-1004", "transaction_time": "2017-01-04 19:26:38.437", "products": [{"qty_sold": 1.0, "product_name": "Mozzarella Classica 4Oz", "product_id": "23046-1004"}, {"qty_sold": 1.02, "product_name": "Agnolotti Black Truffle", "product_id": "7906-1000"}, {"qty_sold": 2.0, "product_name": "Semolina Ciabatta", "product_id": "24142-1000"}, {"qty_sold": 1.0, "product_name": "Rustic Figs", "product_id": "118-1000"}, {"qty_sold": 3.0, "product_name": "Loacker Choc Hznut 118 G", "product_id": "17822-1000"}, {"qty_sold": 1.0, "product_name": "Loacker Lemon Ice Cream 150 G", "product_id": "17615-1000"}], "employee_name": "Michael Tecson"}