{"receipt_id": "430254-1004", "transaction_time": "2017-01-05 14:33:33.700", "products": [{"qty_sold": 1.0, "product_name": "Lettuce Romaine", "product_id": "21921-1000"}, {"qty_sold": 1.0, "product_name": "Bianco Di Martiena 2015", "product_id": "22853-1004"}, {"qty_sold": 1.0, "product_name": "Extra Virgin Olive Oil 16.9 Oz", "product_id": "5598-1000"}, {"qty_sold": 1.0, "product_name": "Onions Scallions", "product_id": "22042-1000"}, {"qty_sold": 0.54, "product_name": "Housemade Ricotta", "product_id": "5581-1000"}, {"qty_sold": 0.42, "product_name": "Mushroom Oyster", "product_id": "21977-1000"}, {"qty_sold": 0.37, "product_name": "Radicchio", "product_id": "22224-1000"}, {"qty_sold": 1.0, "product_name": "Chianti 2014, Certosa", "product_id": "23067-1000"}], "employee_name": "Norma Almazan"}