{"receipt_id": "430718-1004", "transaction_time": "2017-01-05 15:48:39.717", "products": [{"qty_sold": 1.0, "product_name": "Bianca Vesuvio Pasta 17.6Oz", "product_id": "8802-1000"}, {"qty_sold": 1.0, "product_name": "Amarena Cherries In Syrup", "product_id": "15642-1000"}, {"qty_sold": 1.0, "product_name": "Juice Strawberry Lemonade 16Oz", "product_id": "21851-1000"}, {"qty_sold": 1.0, "product_name": "Speak Italian\\Munari Bruno", "product_id": "1716-1000"}], "employee_name": "Sicilia Olvera"}