{"receipt_id": "738511-1005", "transaction_time": "2017-01-02 11:35:36.850", "products": [{"qty_sold": 1.0, "product_name": "Baci White Bulk 0.5 Oz", "product_id": "17642-1000"}, {"qty_sold": 1.0, "product_name": "Baci Milk Bulk 0.5 Oz", "product_id": "17643-1000"}, {"qty_sold": 1.0, "product_name": "Tshirt, All I Want For Xmas, Xl", "product_id": "24684-1000"}, {"qty_sold": 1.0, "product_name": "Loacker Classic Choc 175 G", "product_id": "17594-1000"}, {"qty_sold": 1.0, "product_name": "Bacio - Display", "product_id": "17111-1000"}], "employee_name": "ANNETTE TERRY"}