{"receipt_id": "752235-1005", "transaction_time": "2017-01-03 13:02:07.610", "products": [{"qty_sold": 0.44, "product_name": "Broccoli Crowns", "product_id": "21558-1000"}, {"qty_sold": 1.0, "product_name": "Classic Baguette", "product_id": "193-1000"}, {"qty_sold": 1.0, "product_name": "Radish Bunched", "product_id": "22230-1000"}, {"qty_sold": 0.56, "product_name": "Parmigiano Reggiano 18 Mos", "product_id": "4454-1000"}, {"qty_sold": 2.0, "product_name": "Mayo 1.5Oz", "product_id": "6377-1000"}, {"qty_sold": 1.0, "product_name": "Focaccia Barese Slice", "product_id": "81-1000"}, {"qty_sold": 1.0, "product_name": "Peach Preserves 7.1 Oz", "product_id": "15321-1000"}, {"qty_sold": 2.0, "product_name": "Tomato Cherry Organic", "product_id": "22345-1000"}, {"qty_sold": 0.26, "product_name": "Giorgios Coppa Dolce", "product_id": "16122-1000"}, {"qty_sold": 1.0, "product_name": "Avocado Organic", "product_id": "21501-1000"}, {"qty_sold": 1.0, "product_name": "Berry Gooseberry Cape", "product_id": "21544-1000"}, {"qty_sold": 1.0, "product_name": "Grisbi Choc Cream Fill Cookie", "product_id": "17671-1000"}, {"qty_sold": 1.0, "product_name": "Burratina Antichi 150Gr", "product_id": "4699-1000"}, {"qty_sold": 0.35, "product_name": "Apple Golden Del Org.", "product_id": "21428-1000"}, {"qty_sold": 1.0, "product_name": "Plain Yogurt Berle Farm", "product_id": "23221-1000"}, {"qty_sold": 0.3, "product_name": "Silano Affumicato (Wolf Meadow)", "product_id": "25065-1000"}], "employee_name": "Brittany Reed"}