{"receipt_id": "759591-1005", "transaction_time": "2017-01-03 21:25:54.613", "products": [{"qty_sold": 2.0, "product_name": "Grapefruit Loose Large", "product_id": "21772-1000"}, {"qty_sold": 1.0, "product_name": "Pomegranates", "product_id": "22189-1000"}, {"qty_sold": 1.03, "product_name": "Cherries", "product_id": "21607-1000"}, {"qty_sold": 0.52, "product_name": "Peppers Red Bell", "product_id": "22144-1000"}, {"qty_sold": 1.76, "product_name": "Apple Fuji Org.", "product_id": "21423-1000"}, {"qty_sold": 0.52, "product_name": "Snow Crab Claw", "product_id": "7435-1000"}], "employee_name": "Katherine Cruz"}