{"receipt_id": "769927-1005", "transaction_time": "2017-01-04 20:22:19.497", "products": [{"qty_sold": 1.0, "product_name": "Fc Salad Microgreen 14X1Oz", "product_id": "21701-1000"}, {"qty_sold": 1.0, "product_name": "Onions Scallions Organic", "product_id": "22043-1000"}, {"qty_sold": 0.46, "product_name": "Tomato Heirloom", "product_id": "22355-1000"}, {"qty_sold": 1.0, "product_name": "Dop S.Marzano Tomatoes 14 Oz", "product_id": "15538-1000"}, {"qty_sold": 1.0, "product_name": "Cauliflower", "product_id": "21592-1000"}, {"qty_sold": 1.0, "product_name": "Mozzarella Classica 5 Oz 1Pc", "product_id": "5202-1000"}, {"qty_sold": 1.0, "product_name": "Chicken Stock Small", "product_id": "26094-1000"}, {"qty_sold": 0.3, "product_name": "Fawn", "product_id": "4904-1000"}, {"qty_sold": 1.0, "product_name": "Arcdn Pstrs Large Eggs 1/2Dz", "product_id": "7328-1000"}, {"qty_sold": 0.64, "product_name": "Cascun Farm Chicken Breast", "product_id": "14604-1000"}, {"qty_sold": 1.25, "product_name": "Potato Idaho   80", "product_id": "22200-1000"}], "employee_name": "Shaiasja Rowland"}