{"receipt_id": "775587-1005", "transaction_time": "2017-01-05 14:38:25.247", "products": [{"qty_sold": 0.62, "product_name": "Banana Org.", "product_id": "21503-1000"}, {"qty_sold": 1.0, "product_name": "Mozzarella Di Bufala Antichi", "product_id": "4289-1000"}, {"qty_sold": 0.27, "product_name": "Nodines Double Smoked Bacon", "product_id": "16164-1000"}, {"qty_sold": 1.0, "product_name": "Avocado Organic", "product_id": "21501-1000"}, {"qty_sold": 0.73, "product_name": "Nodines Applewood Smoked Bacon", "product_id": "16166-1000"}, {"qty_sold": 1.08, "product_name": "Cascun Farm Legs", "product_id": "14369-1000"}, {"qty_sold": 0.41, "product_name": "Canestrato Pugliese", "product_id": "5417-1000"}, {"qty_sold": 2.0, "product_name": "Persimmons Fuyu", "product_id": "22151-1000"}, {"qty_sold": 0.58, "product_name": "Tomato Heirloom", "product_id": "22355-1000"}, {"qty_sold": 1.0, "product_name": "Seal Cove Classic Chevre", "product_id": "5147-1000"}], "employee_name": "Panini AM DT Panini AM DT"}