{"receipt_id": "779795-1005", "transaction_time": "2017-01-05 19:12:06.637", "products": [{"qty_sold": 1.0, "product_name": "Rustic Olives", "product_id": "116-1000"}, {"qty_sold": 1.0, "product_name": "Crunch Lemon Cookies 4 Oz", "product_id": "17799-1000"}, {"qty_sold": 1.0, "product_name": "Rustic Prosciutto Cotto & Prov", "product_id": "119-1000"}, {"qty_sold": 0.45, "product_name": "Levoni Mortadella W/ Pistachio", "product_id": "16152-1000"}, {"qty_sold": 1.0, "product_name": "Rubata Olive Breadsticks 7.1Oz", "product_id": "8376-1000"}, {"qty_sold": 1.0, "product_name": "Rigorosa Penne Rigate 17.6Oz", "product_id": "8572-1000"}, {"qty_sold": 1.0, "product_name": "Rosemary Garl Potato Chips 2Oz", "product_id": "9077-1000"}], "employee_name": "Wendy Grandison"}