{"receipt_id": "823172-1006", "transaction_time": "2017-01-02 13:13:05.673", "products": [{"qty_sold": 1.0, "product_name": "Rustic Classico", "product_id": "113-1000"}, {"qty_sold": 0.22, "product_name": "Agnolotti Del Plin Brasato", "product_id": "7896-1000"}, {"qty_sold": 1.0, "product_name": "Sparkling Lemonade 8.45 Fl Oz", "product_id": "1441-1000"}, {"qty_sold": 0.26, "product_name": "Mortadella Plain (Ferrarini)", "product_id": "16138-1000"}, {"qty_sold": 0.4, "product_name": "Salami, Genoa", "product_id": "24971-1000"}, {"qty_sold": 1.0, "product_name": "Herbs Basil", "product_id": "21791-1000"}, {"qty_sold": 1.0, "product_name": "Mozzarella Classica 5 Oz 1Pc", "product_id": "23979-1000"}, {"qty_sold": 0.31, "product_name": "Provolina Valp Sliced", "product_id": "4465-1000"}, {"qty_sold": 1.0, "product_name": "Arborio Rice 17.6 Oz", "product_id": "9171-1000"}, {"qty_sold": 1.0, "product_name": "Bibanesi Pizza Flavor 3.52 Oz", "product_id": "9262-1000"}, {"qty_sold": 1.0, "product_name": "Bottle Deposit", "product_id": "21410-1000"}, {"qty_sold": 0.5, "product_name": "Ravioli Al Prosciutto", "product_id": "7899-1000"}, {"qty_sold": 0.5, "product_name": "Cacio E Pepe Alla Romana", "product_id": "7907-1000"}, {"qty_sold": 1.0, "product_name": "Lemon", "product_id": "21880-1000"}, {"qty_sold": 0.45, "product_name": "Tomato On Vine Backyard Med", "product_id": "22365-1000"}, {"qty_sold": 0.19, "product_name": "Tomato Plum Jumbo", "product_id": "22378-1000"}], "employee_name": "Mirian Cardoso"}