{"receipt_id": "823412-1006", "transaction_time": "2017-01-02 13:17:48.600", "products": [{"qty_sold": 1.0, "product_name": "Herbs Basil", "product_id": "21791-1000"}, {"qty_sold": 1.81, "product_name": "Tomato Cherry Backyard", "product_id": "22342-1000"}, {"qty_sold": 2.0, "product_name": "Linguine", "product_id": "8579-1000"}, {"qty_sold": 0.69, "product_name": "Prosciutto 18 Months - Tanara", "product_id": "16229-1000"}, {"qty_sold": 2.0, "product_name": "Mozzarella Di Bufala Antichi", "product_id": "4289-1000"}], "employee_name": "Marlene Muldrow"}