{"receipt_id": "824848-1006", "transaction_time": "2017-01-02 13:46:53.733", "products": [{"qty_sold": 1.0, "product_name": "Small Artichokes W Herbs In Oi", "product_id": "5751-1000"}, {"qty_sold": 0.66, "product_name": "Guffanti Bergkase", "product_id": "4601-1000"}, {"qty_sold": 0.34, "product_name": "Giorgios Coppa Piccante", "product_id": "16123-1000"}, {"qty_sold": 0.29, "product_name": "Soppressata, Hot", "product_id": "24973-1000"}, {"qty_sold": 1.0, "product_name": "Torinese Breadsticks 7.1 Oz", "product_id": "8381-1000"}, {"qty_sold": 1.0, "product_name": "Whole Wheat Ap Flour 1.5 Lbs", "product_id": "8632-1000"}, {"qty_sold": 1.0, "product_name": "S.Pellegrino Glass 8.45 Oz", "product_id": "1467-1000"}, {"qty_sold": 1.0, "product_name": "Bottle Deposit", "product_id": "21410-1000"}], "employee_name": "Fatima Douelfiqar"}