{"receipt_id": "831092-1006", "transaction_time": "2017-01-02 15:47:43.057", "products": [{"qty_sold": 1.0, "product_name": "Rustic Classico", "product_id": "113-1000"}, {"qty_sold": 1.06, "product_name": "Hot Dogs Beef 1Lb Pack", "product_id": "14696-1000"}, {"qty_sold": 1.0, "product_name": "Tiramisu Classico", "product_id": "23301-1000"}, {"qty_sold": 1.0, "product_name": "Polenta Puffs 3.9 Oz", "product_id": "22866-1000"}, {"qty_sold": 1.0, "product_name": "Mediterranean Hummus", "product_id": "25165-1000"}, {"qty_sold": 1.0, "product_name": "Ricotta Mousse Golosotti", "product_id": "26372-1000"}], "employee_name": "Pastry AM Eataly Boston"}