{"receipt_id": "831140-1006", "transaction_time": "2017-01-02 15:49:12.227", "products": [{"qty_sold": 1.33, "product_name": "Apple Cripps Pink", "product_id": "21231-1002"}, {"qty_sold": 1.0, "product_name": "Rustic Classico", "product_id": "113-1000"}, {"qty_sold": 0.32, "product_name": "Finocchiona Salami", "product_id": "16270-1000"}, {"qty_sold": 1.0, "product_name": "Broccolini Aspiration", "product_id": "21563-1000"}, {"qty_sold": 1.0, "product_name": "Olivias Organics Kale 50Z", "product_id": "25726-1000"}, {"qty_sold": 0.64, "product_name": "Parmigiano Cravero 24Mo", "product_id": "4477-1000"}], "employee_name": "Mirian Cardoso"}