{"receipt_id": "833144-1006", "transaction_time": "2017-01-02 16:29:15.503", "products": [{"qty_sold": 1.0, "product_name": "Half Loaf Otto", "product_id": "22577-1000"}, {"qty_sold": 5.0, "product_name": "Feeling Fork White", "product_id": "9599-1000"}, {"qty_sold": 1.0, "product_name": "Butter Occelli 4.5Oz.", "product_id": "6938-1000"}, {"qty_sold": 0.41, "product_name": "Prosciutto Cotto - Leoncini", "product_id": "16365-1000"}, {"qty_sold": 1.0, "product_name": "Burro 1889 Unsalted", "product_id": "7331-1000"}, {"qty_sold": 0.42, "product_name": "Romaine Heart Baby", "product_id": "22243-1000"}, {"qty_sold": 4.0, "product_name": "Feeling Knife White", "product_id": "9604-1000"}, {"qty_sold": 1.0, "product_name": "Fig Mostarda 8.5 Oz", "product_id": "15201-1000"}, {"qty_sold": 2.0, "product_name": "Truffle Potato Chips 3.53Oz", "product_id": "22758-1000"}, {"qty_sold": 1.0, "product_name": "Balsamic Dressing 8B 3.38Oz", "product_id": "5857-1000"}], "employee_name": "Eleni Biru"}