{"receipt_id": "833288-1006", "transaction_time": "2017-01-02 16:32:24.260", "products": [{"qty_sold": 2.0, "product_name": "Aranciata 9.3 Fl Oz", "product_id": "1425-1000"}, {"qty_sold": 2.0, "product_name": "Bottle Deposit", "product_id": "21410-1000"}, {"qty_sold": 0.65, "product_name": "Spinach Tagliatelle", "product_id": "7968-1000"}, {"qty_sold": 0.64, "product_name": "Squid Ink Tagliatelle", "product_id": "7969-1000"}, {"qty_sold": 0.71, "product_name": "Tagliolini", "product_id": "7980-1000"}, {"qty_sold": 0.57, "product_name": "Grana Padano 12 Mos", "product_id": "4481-1000"}], "employee_name": "Wilnie Dauphine"}