{"receipt_id": "834376-1006", "transaction_time": "2017-01-02 16:57:15.113", "products": [{"qty_sold": 0.18, "product_name": "Giorgios Soppressata Dolce", "product_id": "16345-1000"}, {"qty_sold": 1.0, "product_name": "Green Vegetable Sauce 7.05 Oz", "product_id": "15253-1000"}, {"qty_sold": 0.41, "product_name": "Pecorino Di Pienza Nero", "product_id": "5426-1000"}, {"qty_sold": 1.33, "product_name": "Handmade Gnocchi Sardi", "product_id": "8043-1000"}, {"qty_sold": 1.0, "product_name": "Wild Blueberry Yogurt Smoothie", "product_id": "7010-1000"}, {"qty_sold": 1.0, "product_name": "Tomato Pesto 6.3 Oz", "product_id": "15166-1000"}], "employee_name": "Wilnie Dauphine"}