{"receipt_id": "837844-1006", "transaction_time": "2017-01-02 18:37:46.297", "products": [{"qty_sold": 1.0, "product_name": "Fc Pineapple Chunks 10Oz", "product_id": "21697-1000"}, {"qty_sold": 2.0, "product_name": "Berry Blackberries", "product_id": "21532-1000"}, {"qty_sold": 2.0, "product_name": "Berry Blueberries 4.4Oz", "product_id": "21534-1000"}, {"qty_sold": 2.0, "product_name": "Fc Honeydew Chunks 10Oz", "product_id": "21693-1000"}, {"qty_sold": 1.0, "product_name": "Fc Papaya Chuncks 18X8Oz", "product_id": "21695-1000"}, {"qty_sold": 1.98, "product_name": "Grapes Green Seedless", "product_id": "21776-1000"}, {"qty_sold": 2.0, "product_name": "Fc Mangos Chunks 10Oz", "product_id": "21694-1000"}, {"qty_sold": 1.0, "product_name": "Juice Grapefruit 16Oz", "product_id": "21832-1000"}, {"qty_sold": 6.0, "product_name": "Kiwi", "product_id": "21865-1000"}], "employee_name": "Fatima Douelfiqar"}