{"receipt_id": "839088-1006", "transaction_time": "2017-01-02 19:23:08.583", "products": [{"qty_sold": 1.0, "product_name": "Olivias Organics Kale 50Z", "product_id": "25726-1000"}, {"qty_sold": 1.03, "product_name": "Scallops Nantucket", "product_id": "7499-1000"}, {"qty_sold": 1.0, "product_name": "Tomato Heirloom Kumato", "product_id": "22359-1000"}, {"qty_sold": 1.0, "product_name": "Avocado Hass", "product_id": "21500-1000"}, {"qty_sold": 1.0, "product_name": "Black Bean Sedani 10 Oz", "product_id": "26181-1000"}, {"qty_sold": 1.0, "product_name": "Juice Orange 64Oz", "product_id": "21845-1000"}, {"qty_sold": 1.0, "product_name": "Storyboard Box 5.9 Oz", "product_id": "23506-1000"}, {"qty_sold": 0.85, "product_name": "Potato Yams Jumbo", "product_id": "22211-1000"}], "employee_name": "Fatima Douelfiqar"}