{"receipt_id": "840520-1006", "transaction_time": "2017-01-02 20:30:51.757", "products": [{"qty_sold": 2.0, "product_name": "Classic Mole Cola Soda 12.8 Oz", "product_id": "24568-1000"}, {"qty_sold": 1.0, "product_name": "Tozzetti W/ Chili Pepper 5.2Oz", "product_id": "9261-1000"}, {"qty_sold": 1.0, "product_name": "Pan Di Stelle", "product_id": "17873-1000"}, {"qty_sold": 1.0, "product_name": "Add Cannoli Topping", "product_id": "25761-1000"}, {"qty_sold": 1.0, "product_name": "Bibanesi Breadsticks 3.52 Oz", "product_id": "9066-1000"}, {"qty_sold": 1.0, "product_name": "Cannolo", "product_id": "14840-1000"}, {"qty_sold": 1.0, "product_name": "Abbracci", "product_id": "24053-1000"}, {"qty_sold": 1.0, "product_name": "Sesame Seed Tozzetti 5.29Oz", "product_id": "9257-1000"}], "employee_name": "Ryan McCormick"}