{"receipt_id": "856112-1006", "transaction_time": "2017-01-03 19:38:18.513", "products": [{"qty_sold": 1.0, "product_name": "Pistachio Spread 5.3 Oz", "product_id": "16568-1000"}, {"qty_sold": 1.0, "product_name": "Torrone Almond Nougat 5.3 Oz", "product_id": "16701-1000"}, {"qty_sold": 1.0, "product_name": "Milk Coconut Liquorice Bar 1.8", "product_id": "23175-1000"}, {"qty_sold": 1.0, "product_name": "Rustic Prosciutto Cotto & Prov", "product_id": "119-1000"}], "employee_name": "Joshua Perez"}