{"receipt_id": "859056-1006", "transaction_time": "2017-01-04 09:57:40.420", "products": [{"qty_sold": 0.19, "product_name": "Bresaola, Wagyu", "product_id": "24981-1000"}, {"qty_sold": 1.0, "product_name": "Bibanesi Pizza Flavor 3.52 Oz", "product_id": "9262-1000"}, {"qty_sold": 1.0, "product_name": "Rustic Olives", "product_id": "116-1000"}, {"qty_sold": 0.28, "product_name": "Blu Di Langa", "product_id": "4400-1000"}, {"qty_sold": 1.0, "product_name": "Langherino Di Bosia", "product_id": "5255-1000"}, {"qty_sold": 0.18, "product_name": "Nduja - Salame Di Manzo Wagyu", "product_id": "16506-1000"}], "employee_name": "Fatima Douelfiqar"}