{"receipt_id": "870996-1006", "transaction_time": "2017-01-04 17:41:20.187", "products": [{"qty_sold": 1.0, "product_name": "Berry Blueberries 4.4Oz", "product_id": "21534-1000"}, {"qty_sold": 1.36, "product_name": "Grapes Black Seedless", "product_id": "21774-1000"}, {"qty_sold": 1.42, "product_name": "Red Snapper", "product_id": "7684-1000"}, {"qty_sold": 1.0, "product_name": "Loacker Fondente Dark 37.5 G", "product_id": "17593-1000"}, {"qty_sold": 0.42, "product_name": "Piave Stravecc Red", "product_id": "4503-1000"}, {"qty_sold": 1.0, "product_name": "Olivias Spring Mix  50Z", "product_id": "25728-1000"}, {"qty_sold": 0.74, "product_name": "Apricot Organic", "product_id": "21479-1000"}, {"qty_sold": 0.54, "product_name": "Tomato Cherry Backyard", "product_id": "22342-1000"}], "employee_name": "Max Kuzmin"}