{"receipt_id": "875384-1006", "transaction_time": "2017-01-04 20:42:58.017", "products": [{"qty_sold": 1.0, "product_name": "Bacio - Display", "product_id": "17111-1000"}, {"qty_sold": 0.31, "product_name": "Guffanti Piacentinu Di Ena", "product_id": "5433-1000"}, {"qty_sold": 1.0, "product_name": "Lido Coffee Cup And Saucer", "product_id": "11264-1000"}, {"qty_sold": 1.0, "product_name": "Rustic Prosciutto Cotto & Prov", "product_id": "119-1000"}, {"qty_sold": 1.0, "product_name": "Orange Honey 1Oz", "product_id": "16802-1000"}], "employee_name": "Max Kuzmin"}