{"receipt_id": "876672-1006", "transaction_time": "2017-01-04 22:37:26.097", "products": [{"qty_sold": 1.0, "product_name": "Rustic Olives", "product_id": "116-1000"}, {"qty_sold": 0.26, "product_name": "Onions Shallots", "product_id": "22044-1000"}, {"qty_sold": 0.47, "product_name": "Ricotta Salata Soft Regina", "product_id": "5389-1000"}, {"qty_sold": 1.0, "product_name": "Evoo In Silver Tin 8.45 Oz", "product_id": "6157-1000"}, {"qty_sold": 1.11, "product_name": "Potato Yams Jumbo", "product_id": "22211-1000"}, {"qty_sold": 1.0, "product_name": "Half And Half High Lawn Farm", "product_id": "26045-1000"}, {"qty_sold": 1.0, "product_name": "Carrots Diced 10Oz", "product_id": "21587-1000"}, {"qty_sold": 1.0, "product_name": "Butter Occelli 4.5Oz.", "product_id": "6938-1000"}, {"qty_sold": 0.16, "product_name": "Ginger", "product_id": "22421-1000"}, {"qty_sold": 1.0, "product_name": "Green Olives Snack 1.1 Oz", "product_id": "23242-1000"}], "employee_name": "Natalia Saletnik"}